nafes/__init__.py
nafes/dataset.py
nafes/mutate_labels.py
nafes/mutated_validation.py
nafes/nafes.py
nafes/transform.py
nafes-0.0.4.dist-info/LICENSE
nafes-0.0.4.dist-info/METADATA
nafes-0.0.4.dist-info/WHEEL
nafes-0.0.4.dist-info/top_level.txt
nafes-0.0.4.dist-info/RECORD
