Metadata-Version: 2.2
Name: nafes
Version: 0.0.4
Summary: A python project for prototype-based feature selection
Author-email: Nana Abeka Otoo <nanaabekaotoo@gmail.com>
License: MIT
Project-URL: Homepage, https://github.com/naotoo1/nafes
Project-URL: Repository, https://github.com/naotoo1/nafes
Project-URL: Issues, https://github.com/naotoo1/nafes/issues
Keywords: nafes,feature selection,machine learning,AI
Classifier: Intended Audience :: Developers
Classifier: License :: OSI Approved :: MIT License
Classifier: Natural Language :: English
Classifier: Development Status :: 4 - Beta
Classifier: Intended Audience :: Education
Classifier: Intended Audience :: Science/Research
Classifier: Topic :: Scientific/Engineering :: Artificial Intelligence
Classifier: Topic :: Software Development :: Libraries
Classifier: Topic :: Software Development :: Libraries :: Python Modules
Classifier: License :: OSI Approved :: MIT License
Classifier: Operating System :: OS Independent
Classifier: Programming Language :: Python :: 3.10
Classifier: Programming Language :: Python :: 3.11
Classifier: Programming Language :: Python :: 3.12
Requires-Python: >=3.10
License-File: LICENSE
Requires-Dist: numpy
Requires-Dist: scikit-learn
Requires-Dist: pandas
Requires-Dist: imbalanced-learn
Requires-Dist: torch
Requires-Dist: prototorch
Requires-Dist: prototorch_models
Requires-Dist: pytorch-lightning
Provides-Extra: dev
Requires-Dist: black; extra == "dev"
Requires-Dist: black[jupyter]; extra == "dev"
Requires-Dist: pip; extra == "dev"
Requires-Dist: bump2version; extra == "dev"
Requires-Dist: wheel; extra == "dev"
Requires-Dist: watchdog; extra == "dev"
Requires-Dist: flake8; extra == "dev"
Requires-Dist: tox; extra == "dev"
Requires-Dist: coverage; extra == "dev"
Requires-Dist: Sphinx; extra == "dev"
Requires-Dist: twine; extra == "dev"
Requires-Dist: autopep8; extra == "dev"
Requires-Dist: pytest; extra == "dev"
Provides-Extra: all
Requires-Dist: numpy; extra == "all"
Requires-Dist: scikit-learn; extra == "all"
Requires-Dist: pandas; extra == "all"
Requires-Dist: imbalanced-learn; extra == "all"
Requires-Dist: torch; extra == "all"
Requires-Dist: prototorch; extra == "all"
Requires-Dist: prototorch_models; extra == "all"
Requires-Dist: pytorch-lightning; extra == "all"
Requires-Dist: black; extra == "all"
Requires-Dist: black[jupyter]; extra == "all"
Requires-Dist: pip; extra == "all"
Requires-Dist: bump2version; extra == "all"
Requires-Dist: wheel; extra == "all"
Requires-Dist: watchdog; extra == "all"
Requires-Dist: flake8; extra == "all"
Requires-Dist: tox; extra == "all"
Requires-Dist: coverage; extra == "all"
Requires-Dist: Sphinx; extra == "all"
Requires-Dist: twine; extra == "all"
Requires-Dist: autopep8; extra == "all"
Requires-Dist: pytest; extra == "all"
